microvector/__init__.py
microvector/algos.py
microvector/cache.py
microvector/embed.py
microvector/main.py
microvector/search.py
microvector/store.py
microvector/utils.py
microvector-0.1.29.dist-info/METADATA
microvector-0.1.29.dist-info/WHEEL
microvector-0.1.29.dist-info/licenses/LICENSE
microvector-0.1.29.dist-info/RECORD
