Metadata-Version: 2.4
Name: microvector
Version: 0.1.29
Summary: Lightweight local vector database with persistence to disk, supporting multiple similarity metrics and easy-to-use API.
Project-URL: Homepage, https://github.com/loganpowell/microvector
Project-URL: Repository, https://github.com/loganpowell/microvector
Project-URL: Issues, https://github.com/loganpowell/microvector/issues
Author: John Dagdelen, Logan Powell
License: MIT
License-File: LICENSE
Keywords: automation,database,embeddings,llm,machine-learning,search,similarity,vector
Classifier: Development Status :: 4 - Beta
Classifier: Intended Audience :: Developers
Classifier: Intended Audience :: Science/Research
Classifier: License :: OSI Approved :: MIT License
Classifier: Operating System :: OS Independent
Classifier: Programming Language :: Python :: 3
Classifier: Programming Language :: Python :: 3.10
Classifier: Programming Language :: Python :: 3.11
Classifier: Programming Language :: Python :: 3.12
Classifier: Topic :: Database
Classifier: Topic :: Scientific/Engineering :: Artificial Intelligence
Classifier: Topic :: Software Development :: Libraries :: Python Modules
Classifier: Typing :: Typed
Requires-Python: >=3.10
Requires-Dist: numpy>=1.21.0
Requires-Dist: safetensors>=0.4.0
Requires-Dist: sentence-transformers>=2.0.0
Requires-Dist: torch>=2.6.0
Requires-Dist: transformers>=4.20.0
